{
  "daily": [
    {
      "date": "2026-02-11",
      "total": 186,
      "positive_pct": 6,
      "neutral_pct": 89,
      "negative_pct": 5,
      "themes": {
        "Snow Conditions": 139,
        "Pricing & Value": 2,
        "Summer Activities": 1,
        "Staff & Service": 3,
        "Lift Wait Times": 22,
        "Facilities & Lodging": 1,
        "Environmental Impact": 2,
        "Safety & Incidents": 12,
        "Events & Promotions": 3,
        "Access & Transportation": 1
      },
      "resort_stats": {
        "fortress": {
          "name": "Fortress Mountain",
          "total": 144,
          "positive_pct": 7,
          "neutral_pct": 88,
          "negative_pct": 6
        },
        "castle": {
          "name": "Castle Mountain",
          "total": 22,
          "positive_pct": 9,
          "neutral_pct": 91,
          "negative_pct": 0
        },
        "nakiska": {
          "name": "Nakiska",
          "total": 20,
          "positive_pct": 0,
          "neutral_pct": 95,
          "negative_pct": 5
        }
      }
    },
    {
      "date": "2026-02-12",
      "total": 181,
      "positive_pct": 7,
      "neutral_pct": 88,
      "negative_pct": 5,
      "themes": {
        "Snow Conditions": 134,
        "Pricing & Value": 3,
        "Summer Activities": 1,
        "Staff & Service": 3,
        "Lift Wait Times": 21,
        "Facilities & Lodging": 1,
        "Environmental Impact": 2,
        "Safety & Incidents": 12,
        "Events & Promotions": 3,
        "Access & Transportation": 1
      },
      "resort_stats": {
        "fortress": {
          "name": "Fortress Mountain",
          "total": 139,
          "positive_pct": 7,
          "neutral_pct": 87,
          "negative_pct": 6
        },
        "castle": {
          "name": "Castle Mountain",
          "total": 23,
          "positive_pct": 9,
          "neutral_pct": 91,
          "negative_pct": 0
        },
        "nakiska": {
          "name": "Nakiska",
          "total": 19,
          "positive_pct": 0,
          "neutral_pct": 95,
          "negative_pct": 5
        }
      }
    },
    {
      "date": "2026-02-13",
      "total": 181,
      "positive_pct": 6,
      "neutral_pct": 89,
      "negative_pct": 5,
      "themes": {
        "Snow Conditions": 134,
        "Pricing & Value": 3,
        "Summer Activities": 1,
        "Staff & Service": 3,
        "Lift Wait Times": 22,
        "Facilities & Lodging": 1,
        "Environmental Impact": 2,
        "Safety & Incidents": 11,
        "Events & Promotions": 3,
        "Access & Transportation": 1
      },
      "resort_stats": {
        "fortress": {
          "name": "Fortress Mountain",
          "total": 140,
          "positive_pct": 6,
          "neutral_pct": 88,
          "negative_pct": 6
        },
        "castle": {
          "name": "Castle Mountain",
          "total": 22,
          "positive_pct": 9,
          "neutral_pct": 91,
          "negative_pct": 0
        },
        "nakiska": {
          "name": "Nakiska",
          "total": 19,
          "positive_pct": 0,
          "neutral_pct": 95,
          "negative_pct": 5
        }
      }
    },
    {
      "date": "2026-02-14",
      "total": 788,
      "positive_pct": 9,
      "neutral_pct": 86,
      "negative_pct": 5,
      "themes": {
        "Snow Conditions": 87,
        "Pricing & Value": 13,
        "Summer Activities": 16,
        "Staff & Service": 11,
        "Lift Wait Times": 56,
        "Trails & Recreation": 488,
        "Facilities & Lodging": 34,
        "Access & Transportation": 17,
        "Environmental Impact": 7,
        "Safety & Incidents": 20,
        "Events & Promotions": 5,
        "Family & Beginner Experience": 8,
        "Regulatory Approvals & Land Use": 4,
        "Tourism Strategy & Policy": 21,
        "Environmental Assessment & Compliance": 1
      }
    },
    {
      "date": "2026-02-16",
      "total": 799,
      "positive_pct": 9,
      "neutral_pct": 87,
      "negative_pct": 4,
      "themes": {
        "Snow Conditions": 90,
        "Pricing & Value": 15,
        "Summer Activities": 16,
        "Staff & Service": 10,
        "Lift Wait Times": 57,
        "Trails & Recreation": 483,
        "Facilities & Lodging": 35,
        "Access & Transportation": 19,
        "Environmental Impact": 8,
        "Safety & Incidents": 23,
        "Events & Promotions": 5,
        "Family & Beginner Experience": 7,
        "Regulatory Approvals & Land Use": 5,
        "Tourism Strategy & Policy": 25,
        "Environmental Assessment & Compliance": 1
      }
    },
    {
      "date": "2026-02-17",
      "total": 813,
      "positive_pct": 9,
      "neutral_pct": 86,
      "negative_pct": 5,
      "themes": {
        "Snow Conditions": 91,
        "Pricing & Value": 15,
        "Summer Activities": 14,
        "Staff & Service": 14,
        "Lift Wait Times": 56,
        "Trails & Recreation": 494,
        "Facilities & Lodging": 35,
        "Access & Transportation": 18,
        "Environmental Impact": 8,
        "Safety & Incidents": 26,
        "Events & Promotions": 5,
        "Family & Beginner Experience": 7,
        "Regulatory Approvals & Land Use": 5,
        "Tourism Strategy & Policy": 24,
        "Environmental Assessment & Compliance": 1
      }
    },
    {
      "date": "2026-02-18",
      "total": 805,
      "positive_pct": 9,
      "neutral_pct": 86,
      "negative_pct": 5,
      "themes": {
        "Snow Conditions": 84,
        "Pricing & Value": 13,
        "Summer Activities": 13,
        "Staff & Service": 14,
        "Lift Wait Times": 59,
        "Trails & Recreation": 496,
        "Facilities & Lodging": 32,
        "Access & Transportation": 20,
        "Environmental Impact": 8,
        "Safety & Incidents": 20,
        "Events & Promotions": 5,
        "Family & Beginner Experience": 7,
        "Regulatory Approvals & Land Use": 6,
        "Tourism Strategy & Policy": 27,
        "Environmental Assessment & Compliance": 1
      }
    },
    {
      "date": "2026-02-19",
      "total": 819,
      "positive_pct": 9,
      "neutral_pct": 87,
      "negative_pct": 4,
      "themes": {
        "Snow Conditions": 88,
        "Pricing & Value": 13,
        "Summer Activities": 14,
        "Staff & Service": 13,
        "Lift Wait Times": 58,
        "Trails & Recreation": 507,
        "Facilities & Lodging": 34,
        "Access & Transportation": 18,
        "Environmental Impact": 7,
        "Safety & Incidents": 22,
        "Events & Promotions": 6,
        "Family & Beginner Experience": 6,
        "Regulatory Approvals & Land Use": 5,
        "Tourism Strategy & Policy": 27,
        "Environmental Assessment & Compliance": 1
      }
    }
  ]
}